LICENSE
MANIFEST.in
README.rst
bootstrap.py
buildout.cfg
makefile
requirements.txt
requirements3.txt
setup.py
tox.ini
demo/__init__.py
demo/models.py
demo/urls.py
demo/settings/__init__.py
demo/settings/defaults.py
invites/__init__.py
invites/auth.py
invites/forms.py
invites/models.py
invites/urls.py
invites/utils.py
invites/views.py
invites/management/__init__.py
invites/management/commands/__init__.py
invites/management/commands/invite.py
invites/templates/accounts/account_form.html
invites/templates/accounts/account_login.html
invites/templates/invites/send_invite.html
invites/templates/invites/send_invite_email.html
invites/templates/invites/send_invite_email.txt
invites/tests/__init__.py
invites/tests/conftest.py
invites/tests/test_login.py
invites/tests/test_models.py
invites/tests/test_send_invite.py
invites/tests/data/monkey.jpg
mezzanine_invites.egg-info/PKG-INFO
mezzanine_invites.egg-info/SOURCES.txt
mezzanine_invites.egg-info/dependency_links.txt
mezzanine_invites.egg-info/top_level.txt