Metadata-Version: 1.1
Name: mezzanine-invites
Version: 0.2.3
Summary: Authentication Backend for Mezzanine that allows site registration via alphanumeric invite codes.
Home-page: https://pypi.python.org/pypi/mezzanine-invites
Author: gmf
Author-email: gmflanagan@outlook.com
License: MIT
Download-URL: https://pypi.python.org/packages/source/m/mezzanine-invites/mezzanine-invites-0.2.3.tar.gz
Platform: UNKNOWN
Classifier: Development Status :: 3 - Alpha
Classifier: Intended Audience :: Developers
Classifier: License :: OSI Approved :: MIT License
Classifier: Programming Language :: Python :: 2
Classifier: Programming Language :: Python :: 3
Classifier: Framework :: Django
